diart/__init__.py
diart/argdoc.py
diart/audio.py
diart/features.py
diart/functional.py
diart/inference.py
diart/mapping.py
diart/models.py
diart/operators.py
diart/optim.py
diart/progress.py
diart/sinks.py
diart/sources.py
diart/utils.py
diart/blocks/__init__.py
diart/blocks/aggregation.py
diart/blocks/base.py
diart/blocks/clustering.py
diart/blocks/diarization.py
diart/blocks/embedding.py
diart/blocks/segmentation.py
diart/blocks/utils.py
diart/blocks/vad.py
diart/console/__init__.py
diart/console/benchmark.py
diart/console/client.py
diart/console/serve.py
diart/console/stream.py
diart/console/tune.py
diart-0.9.1.dist-info/LICENSE
diart-0.9.1.dist-info/METADATA
diart-0.9.1.dist-info/WHEEL
diart-0.9.1.dist-info/entry_points.txt
diart-0.9.1.dist-info/top_level.txt
diart-0.9.1.dist-info/RECORD
