Metadata-Version: 2.1
Name: diart
Version: 0.9.1
Summary: A python framework to build AI for real-time speech
Home-page: https://github.com/juanmc2005/diart
Author: Juan Manuel Coria
License: MIT
Keywords: speaker diarization,streaming,online,real time,rxpy
Classifier: Development Status :: 4 - Beta
Classifier: License :: OSI Approved :: MIT License
Classifier: Topic :: Multimedia :: Sound/Audio :: Analysis
Classifier: Topic :: Multimedia :: Sound/Audio :: Speech
Classifier: Topic :: Scientific/Engineering :: Artificial Intelligence
License-File: LICENSE
Requires-Dist: numpy >=1.20.2
Requires-Dist: matplotlib <3.6.0,>=3.3.3
Requires-Dist: rx >=3.2.0
Requires-Dist: scipy >=1.6.0
Requires-Dist: sounddevice >=0.4.2
Requires-Dist: einops >=0.3.0
Requires-Dist: tqdm >=4.64.0
Requires-Dist: pandas >=1.4.2
Requires-Dist: torch >=1.12.1
Requires-Dist: torchvision >=0.14.0
Requires-Dist: torchaudio >=2.0.2
Requires-Dist: pyannote.audio >=2.1.1
Requires-Dist: requests >=2.31.0
Requires-Dist: pyannote.core >=4.5
Requires-Dist: pyannote.database >=4.1.1
Requires-Dist: pyannote.metrics >=3.2
Requires-Dist: optuna >=2.10
Requires-Dist: websocket-server >=0.6.4
Requires-Dist: websocket-client >=0.58.0
Requires-Dist: rich >=12.5.1
Provides-Extra: tests
Requires-Dist: pytest <8.0.0,>=7.4.0 ; extra == 'tests'
Requires-Dist: onnxruntime ==1.18.0 ; extra == 'tests'
